booleangene/__init__.py
booleangene/cli.py
booleangene/run_clustering_analysis.py
booleangene/run_count_loops.py
booleangene/run_lyapunov_analysis.py
booleangene/run_stability_analysis.py
booleangene/run_visualize.py
booleangene/modules/BooleanNetwork.py
booleangene/modules/__init__.py
booleangene/modules/analysis.py
booleangene/modules/canalizing_analysis.py
booleangene/modules/formula_parser.py
booleangene/modules/io_utils.py
booleangene/modules/logic_processing.py
booleangene/modules/qm.py
booleangene/modules/regenerate_network.py
booleangene/modules/visualization_helper.py
booleangene-0.0.3.dist-info/METADATA
booleangene-0.0.3.dist-info/WHEEL
booleangene-0.0.3.dist-info/entry_points.txt
booleangene-0.0.3.dist-info/top_level.txt
booleangene-0.0.3.dist-info/RECORD
