Metadata-Version: 2.4
Name: booleangene
Version: 0.0.3
Summary: Analysis of Boolean gene networks
Author: Chris Viets
Project-URL: Homepage, https://github.com/cviets/booleangene
Project-URL: Bug Tracker, https://github.com/cviets/booleangene/issues
Requires-Python: >=3.6
Requires-Dist: numpy
Requires-Dist: networkx
Requires-Dist: sympy
Requires-Dist: tqdm
